redpepper/version.py
redpepper-0.3.3.dist-info/METADATA
redpepper-0.3.3.dist-info/WHEEL
redpepper-0.3.3.dist-info/licenses/LICENSE.txt
redpepper-0.3.3.dist-info/RECORD
