Metadata-Version: 2.4
Name: redpepper
Version: 0.3.3
Summary: A state-based server management system (meta-package)
Project-URL: Homepage, https://github.com/merlinz01/redpepper
Project-URL: Documentation, https://merlinz01.github.com/redpepper
Project-URL: Repository, https://github.com/merlinz01/redpepper
Project-URL: Bug Tracker, https://github.com/merlinz01/redpepper/issues
Project-URL: Changelog, https://github.com/merlinz01/redpepper/blob/master/CHANGELOG.md
License: MIT License
License-File: LICENSE.txt
Classifier: Development Status :: 3 - Alpha
Classifier: Intended Audience :: Developers
Classifier: Intended Audience :: Information Technology
Classifier: License :: OSI Approved :: MIT License
Classifier: Operating System :: POSIX :: Linux
Classifier: Programming Language :: Python :: 3
Classifier: Topic :: System :: Installation/Setup
Classifier: Topic :: System :: Systems Administration
Requires-Python: >=3.12
Provides-Extra: agent
Requires-Dist: redpepper-agent; extra == 'agent'
Provides-Extra: manager
Requires-Dist: redpepper-manager; extra == 'manager'
Provides-Extra: operations
Requires-Dist: redpepper-operations; extra == 'operations'
Provides-Extra: requests
Requires-Dist: redpepper-requests; extra == 'requests'
Provides-Extra: tools
Requires-Dist: redpepper-tools; extra == 'tools'
